timestrike/__init__.py
timestrike/timing.py
timestrike-0.1.10.dist-info/LICENSE
timestrike-0.1.10.dist-info/METADATA
timestrike-0.1.10.dist-info/WHEEL
timestrike-0.1.10.dist-info/top_level.txt
timestrike-0.1.10.dist-info/RECORD
