Metadata-Version: 2.2
Name: timestrike
Version: 0.1.10
Summary: Timing attacks
License:                     GNU GENERAL PUBLIC LICENSE
Requires-Python: >=3.10
License-File: LICENSE
